{
	"availableLanguageIds": [
		"en_US"
	],
	"defaultLanguageId": "en_US",
	"fields": [
		{
			"dataType": "date",
			"fieldNamespace": "ddm",
			"indexType": "keyword",
			"label": {
				"en_US": "Date"
			},
			"localizable": false,
			"name": "date",
			"predefinedValue": {
				"en_US": ""
			},
			"readOnly": false,
			"repeatable": false,
			"required": false,
			"showLabel": true,
			"tip": {
				"en_US": ""
			},
			"type": "ddm-date"
		}
	],
	"successPage": {
		"body": {},
		"enabled": false,
		"title": {}
	}
}